rtl/imem.v
module imem (
    input wire [31:0] addr, // Address from PC
    output wire [31:0] data // Instruction
);

    // Define memory: 4096 words (16KB)
    reg [31:0] memory [0:4095];

    // Read logic (Combinational / Asynchronous read)
    // RISC-V instructions are 4-byte aligned.
    // We use addr[31:2] to index the word array.
    assign data = memory[addr[31:2]];

endmodule

rtl/alu.v
module alu (
    input wire [31:0] a,
    input wire [31:0] b,
    input wire [3:0] alu_ctrl, // ALU Control Signal
    output reg [31:0] result,
    output wire zero           // Zero flag (for branches)
);

    // ALU Control Codes (defined arbitrarily for now)
    localparam ALU_ADD  = 4'b0000;
    localparam ALU_SUB  = 4'b1000;
    localparam ALU_SLL  = 4'b0001; // Shift Left Logical
    localparam ALU_SLT  = 4'b0010; // Set Less Than (Signed)
    localparam ALU_SLTU = 4'b0011; // Set Less Than Unsigned
    localparam ALU_XOR  = 4'b0100;
    localparam ALU_SRL  = 4'b0101; // Shift Right Logical
    localparam ALU_SRA  = 4'b1101; // Shift Right Arithmetic
    localparam ALU_OR   = 4'b0110;
    localparam ALU_AND  = 4'b0111;
    localparam ALU_LUI  = 4'b1001; // Load Upper Immediate (Pass B)

    always @(*) begin
        case (alu_ctrl)
            ALU_ADD:  result = a + b;
            ALU_SUB:  result = a - b;
            ALU_SLL:  result = a << b[4:0];
            ALU_SLT:  result = ($signed(a) < $signed(b)) ? 32'd1 : 32'd0;
            ALU_SLTU: result = (a < b) ? 32'd1 : 32'd0;
            ALU_XOR:  result = a ^ b;
            ALU_SRL:  result = a >> b[4:0];
            ALU_SRA:  result = $signed(a) >>> b[4:0];
            ALU_OR:   result = a | b;
            ALU_AND:  result = a & b;
            ALU_LUI:  result = b;
            default:  result = 32'b0;
        endcase
    end

    assign zero = (result == 32'b0);

endmodule

rtl/imm_gen.v
module imm_gen (
    input wire [31:0] instr,
    output reg [31:0] imm
);

    wire [6:0] opcode = instr[6:0];

    always @(*) begin
        case (opcode)
            // I-type: [31:20] -> imm[11:0]
            // ADDI, LW, JALR, etc.
            7'b0010011, 7'b0000011, 7'b1100111: 
                imm = {{20{instr[31]}}, instr[31:20]};

            // S-type: [31:25] + [11:7] -> imm[11:0]
            // SW
            7'b0100011: 
                imm = {{20{instr[31]}}, instr[31:25], instr[11:7]};

            // B-type: [31], [7], [30:25], [11:8] -> imm[12:1]
            // BEQ, BNE, etc.
            7'b1100011: 
                imm = {{20{instr[31]}}, instr[7], instr[30:25], instr[11:8], 1'b0};

            // U-type: [31:12] -> imm[31:12]
            // LUI, AUIPC
            7'b0110111, 7'b0010111: 
                imm = {instr[31:12], 12'b0};

            // J-type: [31], [19:12], [20], [30:21] -> imm[20:1]
            // JAL
            7'b1101111: 
                imm = {{12{instr[31]}}, instr[19:12], instr[20], instr[30:21], 1'b0};

            default: 
                imm = 32'b0;
        endcase
    end

endmodule

rtl/regfile.v
module regfile (
    input wire clk,
    input wire we,            // Write Enable
    input wire [4:0] rs1_addr, // Read Address 1
    input wire [4:0] rs2_addr, // Read Address 2
    input wire [4:0] rd_addr,  // Write Address
    input wire [31:0] wdata,   // Write Data
    output wire [31:0] rs1_data, // Read Data 1
    output wire [31:0] rs2_data  // Read Data 2
);

    // 32 registers of 32-bit width
    reg [31:0] regs [0:31];

    integer i;

    // Initialize registers to 0
    initial begin
        for (i = 0; i < 32; i = i + 1) begin
            regs[i] = 32'h0;
        end
        regs[2] = 32'h4000; // Initialize SP to 16KB
    end

    // Write operation (Synchronous)
    // Note: x0 is hardwired to 0, so we never write to it.
    always @(posedge clk) begin
        if (we && (rd_addr != 5'b00000)) begin
            regs[rd_addr] <= wdata;
        end
    end

    // Read operation (Asynchronous)
    // If reading x0, always return 0.
    assign rs1_data = (rs1_addr == 5'b0) ? 32'b0 : regs[rs1_addr];
    assign rs2_data = (rs2_addr == 5'b0) ? 32'b0 : regs[rs2_addr];

endmodule

rtl/decoder.v
module decoder (
    input wire [31:0] instr,
    output wire [6:0] opcode,
    output wire [2:0] funct3,
    output wire [6:0] funct7,
    output wire [4:0] rd,
    output wire [4:0] rs1,
    output wire [4:0] rs2,
    // Control signals (placeholder for now)
    output wire is_r_type,
    output wire is_i_type,
    output wire is_s_type,
    output wire is_b_type,
    output wire is_u_type,
    output wire is_j_type
);

    // Field extraction
    assign opcode = instr[6:0];
    assign rd     = instr[11:7];
    assign funct3 = instr[14:12];
    assign rs1    = instr[19:15];
    assign rs2    = instr[24:20];
    assign funct7 = instr[31:25];

    // Instruction Type Decoding (Based on Opcode)
    // Reference: RISC-V Unprivileged Spec
    
    // R-type: 0110011 (OP)
    assign is_r_type = (opcode == 7'b0110011);

    // I-type: 0010011 (OP-IMM), 0000011 (LOAD), 1100111 (JALR)
    assign is_i_type = (opcode == 7'b0010011) || (opcode == 7'b0000011) || (opcode == 7'b1100111);

    // S-type: 0100011 (STORE)
    assign is_s_type = (opcode == 7'b0100011);

    // B-type: 1100011 (BRANCH)
    assign is_b_type = (opcode == 7'b1100011);

    // U-type: 0110111 (LUI), 0010111 (AUIPC)
    assign is_u_type = (opcode == 7'b0110111) || (opcode == 7'b0010111);

    // J-type: 1101111 (JAL)
    assign is_j_type = (opcode == 7'b1101111);

endmodule

rtl/pc.v
module pc (
    input wire clk,
    input wire rst_n,      // Active low reset
    input wire [31:0] din, // Next PC value
    output reg [31:0] dout // Current PC value
);

    always @(posedge clk or negedge rst_n) begin
        if (!rst_n) begin
            dout <= 32'h00000000; // Reset address
        end else begin
            dout <= din;
        end
    end

endmodule

rtl/core.v
module core (
    input wire clk,
    input wire rst_n,
    input wire [31:0] instr,   // Instruction from IMEM
    output wire [31:0] pc_addr // PC output to IMEM
);

    wire [31:0] pc_next;
    wire [31:0] pc_curr;

    // Instantiate PC
    pc u_pc (
        .clk(clk),
        .rst_n(rst_n),
        .din(pc_next),
        .dout(pc_curr)
    );

    // Decoder signals
    wire [6:0] opcode;
    wire [2:0] funct3;
    wire [6:0] funct7;
    wire [4:0] rd;
    wire [4:0] rs1;
    wire [4:0] rs2;
    wire is_r_type, is_i_type, is_s_type, is_b_type, is_u_type, is_j_type;

    // RegFile signals
    wire reg_write;
    wire [31:0] wdata; // Data to write back to RegFile
    wire [31:0] rs1_data;
    wire [31:0] rs2_data;

    // ALU signals
    wire [31:0] alu_result;
    wire zero_flag;
    wire [3:0] alu_ctrl;
    wire [31:0] alu_src_b; // MUX output for ALU operand B

    // ImmGen signals
    wire [31:0] imm;

    // Instantiate Decoder
    decoder u_decoder (
        .instr(instr),
        .opcode(opcode),
        .funct3(funct3),
        .funct7(funct7),
        .rd(rd),
        .rs1(rs1),
        .rs2(rs2),
        .is_r_type(is_r_type),
        .is_i_type(is_i_type),
        .is_s_type(is_s_type),
        .is_b_type(is_b_type),
        .is_u_type(is_u_type),
        .is_j_type(is_j_type)
    );

    // Instantiate Register File
    regfile u_regfile (
        .clk(clk),
        .we(reg_write),
        .rs1_addr(rs1),
        .rs2_addr(rs2),
        .rd_addr(rd),
        .wdata(wdata),
        .rs1_data(rs1_data),
        .rs2_data(rs2_data)
    );

    // Instantiate Immediate Generator
    imm_gen u_imm_gen (
        .instr(instr),
        .imm(imm)
    );

    // ALU Source B MUX
    // If I-type, S-type, U-type, J-type (basically anything not R-type or Branch), use Immediate
    // Note: Branch comparison uses registers, so it needs rs2.
    // For now, let's simplify: if is_i_type, use imm.
    assign alu_src_b = (is_i_type || is_s_type || is_u_type || is_j_type) ? imm : rs2_data;

    // Instantiate ALU
    alu u_alu (
        .a(rs1_data),
        .b(alu_src_b), 
        .alu_ctrl(alu_ctrl),
        .result(alu_result),
        .zero(zero_flag)
    );

    // Temporary Control Logic (Will be moved to Control Unit later)
    // For now, we only write back for R-type and I-type instructions
    assign reg_write = is_r_type || is_i_type || is_u_type || is_j_type;

    // Temporary ALU Control Logic
    // For now, we just force ADD (0000) to test data path
    assign alu_ctrl = 4'b0000; 

    // Write Back Logic
    // Now we write back the ALU result!
    assign wdata = alu_result;

    // Output current PC to IMEM
    assign pc_addr = pc_curr;

    // Simple PC + 4 logic (Fetch next instruction)
    // This will be replaced by a MUX later for branches/jumps
    assign pc_next = pc_curr + 32'd4;

endmodule

tb/core_tb.v
`timescale 1ns / 1ps

module core_tb;

    reg clk;
    reg rst_n;
    wire [31:0] instr;
    wire [31:0] pc_addr;

    // Instantiate Core
    core u_core (
        .clk(clk),
        .rst_n(rst_n),
        .instr(instr),
        .pc_addr(pc_addr)
    );

    // Instantiate IMEM
    imem u_imem (
        .addr(pc_addr),
        .data(instr)
    );

    // Clock generation
    initial begin
        clk = 0;
        forever #5 clk = ~clk;
    end

    // Test logic
    initial begin
        $dumpfile("wave.vcd");
        $dumpvars(0, core_tb);

        // Reset
        rst_n = 0;
        #20;
        rst_n = 1;

        // Run simulation for a few cycles
        #100;
        $finish;
    end

    // Monitor
    initial begin
        $monitor("Time=%0t | PC=%h | Instr=%h | Op=%b | rd=%d | rs1_d=%h | rs2_d=%h | we=%b | wd=%h", 
                 $time, pc_addr, instr, u_core.opcode, u_core.rd, u_core.rs1_data, u_core.rs2_data, u_core.reg_write, u_core.wdata);
    end

endmodule

sim/wave.vcd
$date
	Tue Dec  2 11:22:00 2025
$end
$version
	Icarus Verilog
$end
$timescale
	1ps
$end
$scope module core_tb $end
$var wire 32 ! pc_addr [31:0] $end
$var wire 32 " instr [31:0] $end
$var reg 1 # clk $end
$var reg 1 $ rst_n $end
$scope module u_core $end
$var wire 4 % alu_ctrl [3:0] $end
$var wire 1 # clk $end
$var wire 32 & pc_addr [31:0] $end
$var wire 1 ' reg_write $end
$var wire 1 $ rst_n $end
$var wire 32 ( wdata [31:0] $end
$var wire 1 ) zero_flag $end
$var wire 32 * rs2_data [31:0] $end
$var wire 5 + rs2 [4:0] $end
$var wire 32 , rs1_data [31:0] $end
$var wire 5 - rs1 [4:0] $end
$var wire 5 . rd [4:0] $end
$var wire 32 / pc_next [31:0] $end
$var wire 32 0 pc_curr [31:0] $end
$var wire 7 1 opcode [6:0] $end
$var wire 1 2 is_u_type $end
$var wire 1 3 is_s_type $end
$var wire 1 4 is_r_type $end
$var wire 1 5 is_j_type $end
$var wire 1 6 is_i_type $end
$var wire 1 7 is_b_type $end
$var wire 32 8 instr [31:0] $end
$var wire 32 9 imm [31:0] $end
$var wire 7 : funct7 [6:0] $end
$var wire 3 ; funct3 [2:0] $end
$var wire 32 < alu_src_b [31:0] $end
$var wire 32 = alu_result [31:0] $end
$scope module u_alu $end
$var wire 4 > alu_ctrl [3:0] $end
$var wire 32 ? b [31:0] $end
$var wire 1 ) zero $end
$var wire 32 @ a [31:0] $end
$var parameter 4 A ALU_ADD $end
$var parameter 4 B ALU_AND $end
$var parameter 4 C ALU_OR $end
$var parameter 4 D ALU_SLL $end
$var parameter 4 E ALU_SLT $end
$var parameter 4 F ALU_SLTU $end
$var parameter 4 G ALU_SRA $end
$var parameter 4 H ALU_SRL $end
$var parameter 4 I ALU_SUB $end
$var parameter 4 J ALU_XOR $end
$var reg 32 K result [31:0] $end
$upscope $end
$scope module u_decoder $end
$var wire 1 6 is_i_type $end
$var wire 1 2 is_u_type $end
$var wire 5 L rs2 [4:0] $end
$var wire 5 M rs1 [4:0] $end
$var wire 5 N rd [4:0] $end
$var wire 7 O opcode [6:0] $end
$var wire 1 3 is_s_type $end
$var wire 1 4 is_r_type $end
$var wire 1 5 is_j_type $end
$var wire 1 7 is_b_type $end
$var wire 32 P instr [31:0] $end
$var wire 7 Q funct7 [6:0] $end
$var wire 3 R funct3 [2:0] $end
$upscope $end
$scope module u_imm_gen $end
$var wire 7 S opcode [6:0] $end
$var wire 32 T instr [31:0] $end
$var reg 32 U imm [31:0] $end
$upscope $end
$scope module u_pc $end
$var wire 1 # clk $end
$var wire 32 V din [31:0] $end
$var wire 1 $ rst_n $end
$var reg 32 W dout [31:0] $end
$upscope $end
$scope module u_regfile $end
$var wire 1 # clk $end
$var wire 5 X rd_addr [4:0] $end
$var wire 5 Y rs1_addr [4:0] $end
$var wire 5 Z rs2_addr [4:0] $end
$var wire 32 [ wdata [31:0] $end
$var wire 1 ' we $end
$var wire 32 \ rs2_data [31:0] $end
$var wire 32 ] rs1_data [31:0] $end
$var integer 32 ^ i [31:0] $end
$upscope $end
$upscope $end
$scope module u_imem $end
$var wire 32 _ addr [31:0] $end
$var wire 32 ` data [31:0] $end
$upscope $end
$upscope $end
$enddefinitions $end
$comment Show the parameter values. $end
$dumpall
b100 J
b1000 I
b101 H
b1101 G
b11 F
b10 E
b1 D
b110 C
b111 B
b0 A
$end
#0
$dumpvars
b10011 `
b0 _
b100000 ^
b0 ]
b0 \
b0 [
b0 Z
b0 Y
b0 X
b0 W
b100 V
b0 U
b10011 T
b10011 S
b0 R
b0 Q
b10011 P
b10011 O
b0 N
b0 M
b0 L
b0 K
b0 @
b0 ?
b0 >
b0 =
b0 <
b0 ;
b0 :
b0 9
b10011 8
07
16
05
04
03
02
b10011 1
b0 0
b100 /
b0 .
b0 -
b0 ,
b0 +
b0 *
1)
b0 (
1'
b0 &
b0 %
0$
0#
b10011 "
b0 !
$end
#5000
1#
#10000
0#
#15000
1#
#20000
0#
1$
#25000
0)
b1 (
b1 [
b1 =
b1 K
b1 <
b1 ?
b1 +
b1 L
b1 Z
b1 .
b1 N
b1 X
b1 9
b1 U
b100000000000010010011 "
b100000000000010010011 8
b100000000000010010011 P
b100000000000010010011 T
b100000000000010010011 `
b1000 /
b1000 V
b100 !
b100 &
b100 _
b100 0
b100 W
1#
#30000
0#
#35000
06
b1 (
b1 [
b1 =
b1 K
b1 ,
b1 @
b1 ]
b0 <
b0 ?
b110011 S
b10 +
b10 L
b10 Z
b1 -
b1 M
b1 Y
b10 .
b10 N
b10 X
14
b110011 1
b110011 O
b0 9
b0 U
b1000001000000100110011 "
b1000001000000100110011 8
b1000001000000100110011 P
b1000001000000100110011 T
b1000001000000100110011 `
b0 *
b0 \
b1100 /
b1100 V
b1000 !
b1000 &
b1000 _
b1000 0
b1000 W
1#
#40000
0#
#45000
x'
x)
bx ,
bx @
bx ]
x6
x2
bx (
bx [
bx =
bx K
bx S
bx :
bx Q
bx +
bx L
bx Z
bx -
bx M
bx Y
bx ;
bx R
bx .
bx N
bx X
x4
x3
x7
x5
bx 1
bx O
bx <
bx ?
bx "
bx 8
bx P
bx T
bx `
bx *
bx \
b10000 /
b10000 V
b1100 !
b1100 &
b1100 _
b1100 0
b1100 W
1#
#50000
0#
#55000
b10100 /
b10100 V
b10000 !
b10000 &
b10000 _
b10000 0
b10000 W
1#
#60000
0#
#65000
b11000 /
b11000 V
b10100 !
b10100 &
b10100 _
b10100 0
b10100 W
1#
#70000
0#
#75000
b11100 /
b11100 V
b11000 !
b11000 &
b11000 _
b11000 0
b11000 W
1#
#80000
0#
#85000
b100000 /
b100000 V
b11100 !
b11100 &
b11100 _
b11100 0
b11100 W
1#
#90000
0#
#95000
b100100 /
b100100 V
b100000 !
b100000 &
b100000 _
b100000 0
b100000 W
1#
#100000
0#
#105000
b101000 /
b101000 V
b100100 !
b100100 &
b100100 _
b100100 0
b100100 W
1#
#110000
0#
#115000
b101100 /
b101100 V
b101000 !
b101000 &
b101000 _
b101000 0
b101000 W
1#
