rtl/imem.v
module imem (
    input wire [31:0] addr, // Address from PC
    output wire [31:0] data // Instruction
);

    // Define memory: 4096 words (16KB)
    reg [31:0] memory [0:4095];

    // Read logic (Combinational / Asynchronous read)
    // RISC-V instructions are 4-byte aligned.
    // We use addr[31:2] to index the word array.
    assign data = memory[addr[31:2]];

endmodule

rtl/regfile.v
module regfile (
    input wire clk,
    input wire we,            // Write Enable
    input wire [4:0] rs1_addr, // Read Address 1
    input wire [4:0] rs2_addr, // Read Address 2
    input wire [4:0] rd_addr,  // Write Address
    input wire [31:0] wdata,   // Write Data
    output wire [31:0] rs1_data, // Read Data 1
    output wire [31:0] rs2_data  // Read Data 2
);

    // 32 registers of 32-bit width
    reg [31:0] regs [0:31];

    integer i;

    // Initialize registers to 0
    initial begin
        for (i = 0; i < 32; i = i + 1) begin
            regs[i] = 32'h0;
        end
    end

    // Write operation (Synchronous)
    // Note: x0 is hardwired to 0, so we never write to it.
    always @(posedge clk) begin
        if (we && (rd_addr != 5'b00000)) begin
            regs[rd_addr] <= wdata;
        end
    end

    // Read operation (Asynchronous)
    // If reading x0, always return 0.
    assign rs1_data = (rs1_addr == 5'b0) ? 32'b0 : regs[rs1_addr];
    assign rs2_data = (rs2_addr == 5'b0) ? 32'b0 : regs[rs2_addr];

endmodule

rtl/decoder.v
module decoder (
    input wire [31:0] instr,
    output wire [6:0] opcode,
    output wire [2:0] funct3,
    output wire [6:0] funct7,
    output wire [4:0] rd,
    output wire [4:0] rs1,
    output wire [4:0] rs2,
    // Control signals (placeholder for now)
    output wire is_r_type,
    output wire is_i_type,
    output wire is_s_type,
    output wire is_b_type,
    output wire is_u_type,
    output wire is_j_type
);

    // Field extraction
    assign opcode = instr[6:0];
    assign rd     = instr[11:7];
    assign funct3 = instr[14:12];
    assign rs1    = instr[19:15];
    assign rs2    = instr[24:20];
    assign funct7 = instr[31:25];

    // Instruction Type Decoding (Based on Opcode)
    // Reference: RISC-V Unprivileged Spec
    
    // R-type: 0110011 (OP)
    assign is_r_type = (opcode == 7'b0110011);

    // I-type: 0010011 (OP-IMM), 0000011 (LOAD), 1100111 (JALR)
    assign is_i_type = (opcode == 7'b0010011) || (opcode == 7'b0000011) || (opcode == 7'b1100111);

    // S-type: 0100011 (STORE)
    assign is_s_type = (opcode == 7'b0100011);

    // B-type: 1100011 (BRANCH)
    assign is_b_type = (opcode == 7'b1100011);

    // U-type: 0110111 (LUI), 0010111 (AUIPC)
    assign is_u_type = (opcode == 7'b0110111) || (opcode == 7'b0010111);

    // J-type: 1101111 (JAL)
    assign is_j_type = (opcode == 7'b1101111);

endmodule

rtl/pc.v
module pc (
    input wire clk,
    input wire rst_n,      // Active low reset
    input wire [31:0] din, // Next PC value
    output reg [31:0] dout // Current PC value
);

    always @(posedge clk or negedge rst_n) begin
        if (!rst_n) begin
            dout <= 32'h00000000; // Reset address
        end else begin
            dout <= din;
        end
    end

endmodule

rtl/core.v
module core (
    input wire clk,
    input wire rst_n,
    input wire [31:0] instr,   // Instruction from IMEM
    output wire [31:0] pc_addr // PC output to IMEM
);

    wire [31:0] pc_next;
    wire [31:0] pc_curr;

    // Instantiate PC
    pc u_pc (
        .clk(clk),
        .rst_n(rst_n),
        .din(pc_next),
        .dout(pc_curr)
    );

    // Decoder signals
    wire [6:0] opcode;
    wire [2:0] funct3;
    wire [6:0] funct7;
    wire [4:0] rd;
    wire [4:0] rs1;
    wire [4:0] rs2;
    wire is_r_type, is_i_type, is_s_type, is_b_type, is_u_type, is_j_type;

    // RegFile signals
    wire reg_write;
    wire [31:0] wdata; // Data to write back to RegFile
    wire [31:0] rs1_data;
    wire [31:0] rs2_data;

    // Instantiate Decoder
    decoder u_decoder (
        .instr(instr),
        .opcode(opcode),
        .funct3(funct3),
        .funct7(funct7),
        .rd(rd),
        .rs1(rs1),
        .rs2(rs2),
        .is_r_type(is_r_type),
        .is_i_type(is_i_type),
        .is_s_type(is_s_type),
        .is_b_type(is_b_type),
        .is_u_type(is_u_type),
        .is_j_type(is_j_type)
    );

    // Instantiate Register File
    regfile u_regfile (
        .clk(clk),
        .we(reg_write),
        .rs1_addr(rs1),
        .rs2_addr(rs2),
        .rd_addr(rd),
        .wdata(wdata),
        .rs1_data(rs1_data),
        .rs2_data(rs2_data)
    );

    // Temporary Control Logic (Will be moved to Control Unit later)
    // For now, we only write back for R-type and I-type instructions
    assign reg_write = is_r_type || is_i_type || is_u_type || is_j_type;

    // Temporary Write Back Logic
    // For now, we just write back a dummy value (e.g., 0xDEADBEEF) to test RegFile write
    // Later this will come from ALU or Memory
    assign wdata = 32'hDEADBEEF;

    // Output current PC to IMEM
    assign pc_addr = pc_curr;

    // Simple PC + 4 logic (Fetch next instruction)
    // This will be replaced by a MUX later for branches/jumps
    assign pc_next = pc_curr + 32'd4;

endmodule

tb/core_tb.v
`timescale 1ns / 1ps

module core_tb;

    reg clk;
    reg rst_n;
    wire [31:0] instr;
    wire [31:0] pc_addr;

    // Instantiate Core
    core u_core (
        .clk(clk),
        .rst_n(rst_n),
        .instr(instr),
        .pc_addr(pc_addr)
    );

    // Instantiate IMEM
    imem u_imem (
        .addr(pc_addr),
        .data(instr)
    );

    // Clock generation
    initial begin
        clk = 0;
        forever #5 clk = ~clk;
    end

    // Test logic
    initial begin
        $dumpfile("wave.vcd");
        $dumpvars(0, core_tb);

        // Reset
        rst_n = 0;
        #20;
        rst_n = 1;

        // Run simulation for a few cycles
        #100;
        $finish;
    end

    // Monitor
    initial begin
        $monitor("Time=%0t | PC=%h | Instr=%h | Op=%b | rd=%d | rs1_d=%h | rs2_d=%h | we=%b | wd=%h", 
                 $time, pc_addr, instr, u_core.opcode, u_core.rd, u_core.rs1_data, u_core.rs2_data, u_core.reg_write, u_core.wdata);
    end

endmodule

sim/wave.vcd
$date
	Tue Dec  2 11:00:38 2025
$end
$version
	Icarus Verilog
$end
$timescale
	1ps
$end
$scope module core_tb $end
$var wire 32 ! pc_addr [31:0] $end
$var wire 32 " instr [31:0] $end
$var reg 1 # clk $end
$var reg 1 $ rst_n $end
$scope module u_core $end
$var wire 1 # clk $end
$var wire 32 % pc_addr [31:0] $end
$var wire 1 & reg_write $end
$var wire 1 $ rst_n $end
$var wire 32 ' wdata [31:0] $end
$var wire 32 ( rs2_data [31:0] $end
$var wire 5 ) rs2 [4:0] $end
$var wire 32 * rs1_data [31:0] $end
$var wire 5 + rs1 [4:0] $end
$var wire 5 , rd [4:0] $end
$var wire 32 - pc_next [31:0] $end
$var wire 32 . pc_curr [31:0] $end
$var wire 7 / opcode [6:0] $end
$var wire 1 0 is_u_type $end
$var wire 1 1 is_s_type $end
$var wire 1 2 is_r_type $end
$var wire 1 3 is_j_type $end
$var wire 1 4 is_i_type $end
$var wire 1 5 is_b_type $end
$var wire 32 6 instr [31:0] $end
$var wire 7 7 funct7 [6:0] $end
$var wire 3 8 funct3 [2:0] $end
$scope module u_decoder $end
$var wire 1 4 is_i_type $end
$var wire 1 0 is_u_type $end
$var wire 5 9 rs2 [4:0] $end
$var wire 5 : rs1 [4:0] $end
$var wire 5 ; rd [4:0] $end
$var wire 7 < opcode [6:0] $end
$var wire 1 1 is_s_type $end
$var wire 1 2 is_r_type $end
$var wire 1 3 is_j_type $end
$var wire 1 5 is_b_type $end
$var wire 32 = instr [31:0] $end
$var wire 7 > funct7 [6:0] $end
$var wire 3 ? funct3 [2:0] $end
$upscope $end
$scope module u_pc $end
$var wire 1 # clk $end
$var wire 32 @ din [31:0] $end
$var wire 1 $ rst_n $end
$var reg 32 A dout [31:0] $end
$upscope $end
$scope module u_regfile $end
$var wire 1 # clk $end
$var wire 5 B rd_addr [4:0] $end
$var wire 5 C rs1_addr [4:0] $end
$var wire 5 D rs2_addr [4:0] $end
$var wire 32 E wdata [31:0] $end
$var wire 1 & we $end
$var wire 32 F rs2_data [31:0] $end
$var wire 32 G rs1_data [31:0] $end
$var integer 32 H i [31:0] $end
$upscope $end
$upscope $end
$scope module u_imem $end
$var wire 32 I addr [31:0] $end
$var wire 32 J data [31:0] $end
$upscope $end
$upscope $end
$enddefinitions $end
$comment Show the parameter values. $end
$dumpall
$end
#0
$dumpvars
b10011 J
b0 I
b100000 H
b0 G
b0 F
b11011110101011011011111011101111 E
b0 D
b0 C
b0 B
b0 A
b100 @
b0 ?
b0 >
b10011 =
b10011 <
b0 ;
b0 :
b0 9
b0 8
b0 7
b10011 6
05
14
03
02
01
00
b10011 /
b0 .
b100 -
b0 ,
b0 +
b0 *
b0 )
b0 (
b11011110101011011011111011101111 '
1&
b0 %
0$
0#
b10011 "
b0 !
$end
#5000
1#
#10000
0#
#15000
1#
#20000
0#
1$
#25000
b1 )
b1 9
b1 D
b1 ,
b1 ;
b1 B
b100000000000010010011 "
b100000000000010010011 6
b100000000000010010011 =
b100000000000010010011 J
b1000 -
b1000 @
b100 !
b100 %
b100 I
b100 .
b100 A
1#
#30000
0#
#35000
04
b11011110101011011011111011101111 *
b11011110101011011011111011101111 G
b10 )
b10 9
b10 D
b1 +
b1 :
b1 C
b10 ,
b10 ;
b10 B
12
b110011 /
b110011 <
b1000001000000100110011 "
b1000001000000100110011 6
b1000001000000100110011 =
b1000001000000100110011 J
b0 (
b0 F
b1100 -
b1100 @
b1000 !
b1000 %
b1000 I
b1000 .
b1000 A
1#
#40000
0#
#45000
x&
bx *
bx G
x4
x0
bx 7
bx >
bx )
bx 9
bx D
bx +
bx :
bx C
bx 8
bx ?
bx ,
bx ;
bx B
x2
x1
x5
x3
bx /
bx <
bx "
bx 6
bx =
bx J
bx (
bx F
b10000 -
b10000 @
b1100 !
b1100 %
b1100 I
b1100 .
b1100 A
1#
#50000
0#
#55000
b10100 -
b10100 @
b10000 !
b10000 %
b10000 I
b10000 .
b10000 A
1#
#60000
0#
#65000
b11000 -
b11000 @
b10100 !
b10100 %
b10100 I
b10100 .
b10100 A
1#
#70000
0#
#75000
b11100 -
b11100 @
b11000 !
b11000 %
b11000 I
b11000 .
b11000 A
1#
#80000
0#
#85000
b100000 -
b100000 @
b11100 !
b11100 %
b11100 I
b11100 .
b11100 A
1#
#90000
0#
#95000
b100100 -
b100100 @
b100000 !
b100000 %
b100000 I
b100000 .
b100000 A
1#
#100000
0#
#105000
b101000 -
b101000 @
b100100 !
b100100 %
b100100 I
b100100 .
b100100 A
1#
#110000
0#
#115000
b101100 -
b101100 @
b101000 !
b101000 %
b101000 I
b101000 .
b101000 A
1#
