rtl/imem.v
module imem (
    input wire [31:0] addr, // Address from PC
    output wire [31:0] data // Instruction
);

    // Define memory: 4096 words (16KB)
    reg [31:0] memory [0:4095];

    // Read logic (Combinational / Asynchronous read)
    // RISC-V instructions are 4-byte aligned.
    // We use addr[31:2] to index the word array.
    assign data = memory[addr[31:2]];

endmodule

rtl/dmem.v
module dmem (
    input wire clk,
    input wire we,
    input wire [31:0] addr,
    input wire [31:0] wdata,
    output wire [31:0] rdata
);

    // 16KB Memory
    reg [31:0] memory [0:4095];

    // Write (Synchronous)
    always @(posedge clk) begin
        if (we) begin
            // Word aligned access, masked to 16KB
            memory[addr[13:2]] <= wdata;
        end
    end

    // Read (Asynchronous/Combinational)
    assign rdata = memory[addr[13:2]];

endmodule

rtl/alu.v
module alu (
    input wire [31:0] a,
    input wire [31:0] b,
    input wire [3:0] alu_ctrl, // ALU Control Signal
    output reg [31:0] result,
    output wire zero           // Zero flag (for branches)
);

    // ALU Control Codes (defined arbitrarily for now)
    localparam ALU_ADD  = 4'b0000;
    localparam ALU_SUB  = 4'b1000;
    localparam ALU_SLL  = 4'b0001; // Shift Left Logical
    localparam ALU_SLT  = 4'b0010; // Set Less Than (Signed)
    localparam ALU_SLTU = 4'b0011; // Set Less Than Unsigned
    localparam ALU_XOR  = 4'b0100;
    localparam ALU_SRL  = 4'b0101; // Shift Right Logical
    localparam ALU_SRA  = 4'b1101; // Shift Right Arithmetic
    localparam ALU_OR   = 4'b0110;
    localparam ALU_AND  = 4'b0111;
    localparam ALU_LUI  = 4'b1001; // Load Upper Immediate (Pass B)

    always @(*) begin
        case (alu_ctrl)
            ALU_ADD:  result = a + b;
            ALU_SUB:  result = a - b;
            ALU_SLL:  result = a << b[4:0];
            ALU_SLT:  result = ($signed(a) < $signed(b)) ? 32'd1 : 32'd0;
            ALU_SLTU: result = (a < b) ? 32'd1 : 32'd0;
            ALU_XOR:  result = a ^ b;
            ALU_SRL:  result = a >> b[4:0];
            ALU_SRA:  result = $signed(a) >>> b[4:0];
            ALU_OR:   result = a | b;
            ALU_AND:  result = a & b;
            ALU_LUI:  result = b;
            default:  result = 32'b0;
        endcase
    end

    assign zero = (result == 32'b0);

endmodule

rtl/alu_control.v
module alu_control (
    input wire [1:0] alu_op,    // From Main Control (to be implemented)
    input wire [2:0] funct3,
    input wire [6:0] funct7,
    output reg [3:0] alu_ctrl
);

    // ALU Control Codes (Must match alu.v)
    localparam ALU_ADD  = 4'b0000;
    localparam ALU_SUB  = 4'b1000;
    localparam ALU_SLL  = 4'b0001;
    localparam ALU_SLT  = 4'b0010;
    localparam ALU_SLTU = 4'b0011;
    localparam ALU_XOR  = 4'b0100;
    localparam ALU_SRL  = 4'b0101;
    localparam ALU_SRA  = 4'b1101;
    localparam ALU_OR   = 4'b0110;
    localparam ALU_AND  = 4'b0111;

    always @(*) begin
        case (alu_op)
            2'b00: begin // LW, SW (Add)
                alu_ctrl = ALU_ADD;
            end
            
            2'b01: begin // BEQ, BNE (Sub)
                alu_ctrl = ALU_SUB;
            end

            2'b10: begin // R-type
                case (funct3)
                    3'b000: alu_ctrl = (funct7[5]) ? ALU_SUB : ALU_ADD; // ADD/SUB
                    3'b001: alu_ctrl = ALU_SLL;                         // SLL
                    3'b010: alu_ctrl = ALU_SLT;                         // SLT
                    3'b011: alu_ctrl = ALU_SLTU;                        // SLTU
                    3'b100: alu_ctrl = ALU_XOR;                         // XOR
                    3'b101: alu_ctrl = (funct7[5]) ? ALU_SRA : ALU_SRL; // SRL/SRA
                    3'b110: alu_ctrl = ALU_OR;                          // OR
                    3'b111: alu_ctrl = ALU_AND;                         // AND
                    default: alu_ctrl = ALU_ADD;
                endcase
            end

            2'b11: begin // I-type (Immediate Arithmetic)
                case (funct3)
                    3'b000: alu_ctrl = ALU_ADD;                         // ADDI
                    3'b001: alu_ctrl = ALU_SLL;                         // SLLI
                    3'b010: alu_ctrl = ALU_SLT;                         // SLTI
                    3'b011: alu_ctrl = ALU_SLTU;                        // SLTIU
                    3'b100: alu_ctrl = ALU_XOR;                         // XORI
                    3'b101: alu_ctrl = (funct7[5]) ? ALU_SRA : ALU_SRL; // SRLI/SRAI
                    3'b110: alu_ctrl = ALU_OR;                          // ORI
                    3'b111: alu_ctrl = ALU_AND;                         // ANDI
                    default: alu_ctrl = ALU_ADD;
                endcase
            end

            default: alu_ctrl = ALU_ADD;
        endcase
    end

endmodule

rtl/imm_gen.v
module imm_gen (
    input wire [31:0] instr,
    output reg [31:0] imm
);

    wire [6:0] opcode = instr[6:0];

    always @(*) begin
        case (opcode)
            // I-type: [31:20] -> imm[11:0]
            // ADDI, LW, JALR, etc.
            7'b0010011, 7'b0000011, 7'b1100111: 
                imm = {{20{instr[31]}}, instr[31:20]};

            // S-type: [31:25] + [11:7] -> imm[11:0]
            // SW
            7'b0100011: 
                imm = {{20{instr[31]}}, instr[31:25], instr[11:7]};

            // B-type: [31], [7], [30:25], [11:8] -> imm[12:1]
            // BEQ, BNE, etc.
            7'b1100011: 
                imm = {{20{instr[31]}}, instr[7], instr[30:25], instr[11:8], 1'b0};

            // U-type: [31:12] -> imm[31:12]
            // LUI, AUIPC
            7'b0110111, 7'b0010111: 
                imm = {instr[31:12], 12'b0};

            // J-type: [31], [19:12], [20], [30:21] -> imm[20:1]
            // JAL
            7'b1101111: 
                imm = {{12{instr[31]}}, instr[19:12], instr[20], instr[30:21], 1'b0};

            default: 
                imm = 32'b0;
        endcase
    end

endmodule

rtl/regfile.v
module regfile (
    input wire clk,
    input wire we,            // Write Enable
    input wire [4:0] rs1_addr, // Read Address 1
    input wire [4:0] rs2_addr, // Read Address 2
    input wire [4:0] rd_addr,  // Write Address
    input wire [31:0] wdata,   // Write Data
    output wire [31:0] rs1_data, // Read Data 1
    output wire [31:0] rs2_data  // Read Data 2
);

    // 32 registers of 32-bit width
    reg [31:0] regs [0:31];

    integer i;

    // Initialize registers to 0
    initial begin
        for (i = 0; i < 32; i = i + 1) begin
            regs[i] = 32'h0;
        end
        regs[2] = 32'h4000; // Initialize SP to 16KB
    end

    // Write operation (Synchronous)
    // Note: x0 is hardwired to 0, so we never write to it.
    always @(posedge clk) begin
        if (we && (rd_addr != 5'b00000)) begin
            regs[rd_addr] <= wdata;
        end
    end

    // Read operation (Asynchronous)
    // If reading x0, always return 0.
    assign rs1_data = (rs1_addr == 5'b0) ? 32'b0 : regs[rs1_addr];
    assign rs2_data = (rs2_addr == 5'b0) ? 32'b0 : regs[rs2_addr];

endmodule

rtl/decoder.v
module decoder (
    input wire [31:0] instr,
    output wire [6:0] opcode,
    output wire [2:0] funct3,
    output wire [6:0] funct7,
    output wire [4:0] rd,
    output wire [4:0] rs1,
    output wire [4:0] rs2,
    // Control signals (placeholder for now)
    output wire is_r_type,
    output wire is_i_type,
    output wire is_s_type,
    output wire is_b_type,
    output wire is_u_type,
    output wire is_j_type,
    output wire is_load,  // New: Explicit Load signal
    output wire is_store  // New: Explicit Store signal
);

    // Field extraction
    assign opcode = instr[6:0];
    assign rd     = instr[11:7];
    assign funct3 = instr[14:12];
    assign rs1    = instr[19:15];
    assign rs2    = instr[24:20];
    assign funct7 = instr[31:25];

    // Instruction Type Decoding
    
    // R-type: 0110011 (OP)
    assign is_r_type = (opcode == 7'b0110011);

    // I-type: 0010011 (OP-IMM), 0000011 (LOAD), 1100111 (JALR)
    assign is_i_type = (opcode == 7'b0010011) || (opcode == 7'b0000011) || (opcode == 7'b1100111);

    // S-type: 0100011 (STORE)
    assign is_s_type = (opcode == 7'b0100011);

    // B-type: 1100011 (BRANCH)
    assign is_b_type = (opcode == 7'b1100011);

    // U-type: 0110111 (LUI), 0010111 (AUIPC)
    assign is_u_type = (opcode == 7'b0110111) || (opcode == 7'b0010111);

    // J-type: 1101111 (JAL)
    assign is_j_type = (opcode == 7'b1101111);

    // Specific Opcode Checks
    assign is_load  = (opcode == 7'b0000011);
    assign is_store = (opcode == 7'b0100011);

endmodule

rtl/pc.v
module pc (
    input wire clk,
    input wire rst_n,      // Active low reset
    input wire [31:0] din, // Next PC value
    output reg [31:0] dout // Current PC value
);

    always @(posedge clk or negedge rst_n) begin
        if (!rst_n) begin
            dout <= 32'h00000000; // Reset address
        end else begin
            dout <= din;
        end
    end

endmodule

rtl/core.v
module core (
    input wire clk,
    input wire rst_n,
    input wire [31:0] instr,   // Instruction from IMEM
    output wire [31:0] pc_addr // PC output to IMEM
);

    wire [31:0] pc_next;
    wire [31:0] pc_curr;

    // Instantiate PC
    pc u_pc (
        .clk(clk),
        .rst_n(rst_n),
        .din(pc_next),
        .dout(pc_curr)
    );

    // Decoder signals
    wire [6:0] opcode;
    wire [2:0] funct3;
    wire [6:0] funct7;
    wire [4:0] rd;
    wire [4:0] rs1;
    wire [4:0] rs2;
    wire is_r_type, is_i_type, is_s_type, is_b_type, is_u_type, is_j_type;
    wire is_load, is_store;

    // RegFile signals
    wire reg_write;
    wire [31:0] wdata; // Data to write back to RegFile
    wire [31:0] rs1_data;
    wire [31:0] rs2_data;

    // ALU signals
    wire [31:0] alu_result;
    wire zero_flag;
    wire [3:0] alu_ctrl;
    wire [31:0] alu_src_b; // MUX output for ALU operand B

    // DMEM signals
    wire [31:0] dmem_rdata;
    wire mem_write;
    wire mem_to_reg;

    // ImmGen signals
    wire [31:0] imm;

    // Control signals
    wire [1:0] alu_op;

    // Instantiate Decoder
    decoder u_decoder (
        .instr(instr),
        .opcode(opcode),
        .funct3(funct3),
        .funct7(funct7),
        .rd(rd),
        .rs1(rs1),
        .rs2(rs2),
        .is_r_type(is_r_type),
        .is_i_type(is_i_type),
        .is_s_type(is_s_type),
        .is_b_type(is_b_type),
        .is_u_type(is_u_type),
        .is_j_type(is_j_type),
        .is_load(is_load),
        .is_store(is_store)
    );

    // Instantiate Register File
    regfile u_regfile (
        .clk(clk),
        .we(reg_write),
        .rs1_addr(rs1),
        .rs2_addr(rs2),
        .rd_addr(rd),
        .wdata(wdata),
        .rs1_data(rs1_data),
        .rs2_data(rs2_data)
    );

    // Instantiate Immediate Generator
    imm_gen u_imm_gen (
        .instr(instr),
        .imm(imm)
    );

    // Instantiate ALU Control
    alu_control u_alu_control (
        .alu_op(alu_op),
        .funct3(funct3),
        .funct7(funct7),
        .alu_ctrl(alu_ctrl)
    );

    // MUX for ALU operand B
    // I-type/S-type/U-type/J-type use Immediate
    assign alu_src_b = (is_i_type || is_s_type || is_u_type || is_j_type) ? imm : rs2_data;

    // Instantiate ALU
    alu u_alu (
        .a(rs1_data),
        .b(alu_src_b), 
        .alu_ctrl(alu_ctrl),
        .result(alu_result),
        .zero(zero_flag)
    );

    // Instantiate Data Memory
    dmem u_dmem (
        .clk(clk),
        .we(mem_write),
        .addr(alu_result),
        .wdata(rs2_data),
        .rdata(dmem_rdata)
    );

    // Control Logic (temporary)
    assign reg_write = is_r_type || is_i_type || is_u_type || is_j_type; // Load is I-type
    assign mem_write = is_store;
    assign mem_to_reg = is_load;

    // Generate ALU Op (temporary)
    // 00: LW/SW, 01: Branch, 10: R-type, 11: I-type
    assign alu_op[1] = is_r_type || (is_i_type && !is_load); // Don't use I-type ALU logic for Load (use Add)
    assign alu_op[0] = is_b_type || (is_i_type && !is_load);

    // Write back data MUX
    assign wdata = mem_to_reg ? dmem_rdata : 
                   is_j_type ? (pc_curr + 32'd4) : // JAL/JALR write PC+4 to rd
                   alu_result;

    // Branch/Jump Logic
    wire branch_taken = is_b_type && zero_flag; // BEQ: take branch if Zero (TODO: support BNE, BLT etc)
    wire jump_taken   = is_j_type; // JAL

    // PC Next MUX
    // Priority: Jump > Branch > Next
    assign pc_next = jump_taken   ? (pc_curr + imm) : // JAL target = PC + offset
                     branch_taken ? (pc_curr + imm) : // Branch target = PC + offset
                     (pc_curr + 32'd4);               // Default next instruction

    // Output current PC to IMEM
    assign pc_addr = pc_curr;

endmodule

tb/core_tb.v
`timescale 1ns / 1ps

module core_tb;

    reg clk;
    reg rst_n;
    wire [31:0] instr;
    wire [31:0] pc_addr;

    // Instantiate Core
    core u_core (
        .clk(clk),
        .rst_n(rst_n),
        .instr(instr),
        .pc_addr(pc_addr)
    );

    // Instantiate IMEM
    imem u_imem (
        .addr(pc_addr),
        .data(instr)
    );

    // Clock generation
    initial begin
        clk = 0;
        forever #5 clk = ~clk;
    end

    // Test logic
    initial begin
        $dumpfile("wave.vcd");
        $dumpvars(0, core_tb);

        // Reset
        rst_n = 0;
        #20;
        rst_n = 1;

        // Run simulation for a few cycles
        #100;
        $finish;
    end

    // Monitor
    initial begin
        $monitor("Time=%0t | PC=%h | Instr=%h | Op=%b | rd=%d | rs1_d=%h | rs2_d=%h | we=%b | wd=%h", 
                 $time, pc_addr, instr, u_core.opcode, u_core.rd, u_core.rs1_data, u_core.rs2_data, u_core.reg_write, u_core.wdata);
    end

endmodule

sim/wave.vcd
$date
	Tue Dec  2 11:45:08 2025
$end
$version
	Icarus Verilog
$end
$timescale
	1ps
$end
$scope module core_tb $end
$var wire 32 ! pc_addr [31:0] $end
$var wire 32 " instr [31:0] $end
$var reg 1 # clk $end
$var reg 1 $ rst_n $end
$scope module u_core $end
$var wire 1 % branch_taken $end
$var wire 1 # clk $end
$var wire 1 & jump_taken $end
$var wire 1 ' mem_to_reg $end
$var wire 1 ( mem_write $end
$var wire 32 ) pc_addr [31:0] $end
$var wire 1 * reg_write $end
$var wire 1 $ rst_n $end
$var wire 1 + zero_flag $end
$var wire 32 , wdata [31:0] $end
$var wire 32 - rs2_data [31:0] $end
$var wire 5 . rs2 [4:0] $end
$var wire 32 / rs1_data [31:0] $end
$var wire 5 0 rs1 [4:0] $end
$var wire 5 1 rd [4:0] $end
$var wire 32 2 pc_next [31:0] $end
$var wire 32 3 pc_curr [31:0] $end
$var wire 7 4 opcode [6:0] $end
$var wire 1 5 is_u_type $end
$var wire 1 6 is_store $end
$var wire 1 7 is_s_type $end
$var wire 1 8 is_r_type $end
$var wire 1 9 is_load $end
$var wire 1 : is_j_type $end
$var wire 1 ; is_i_type $end
$var wire 1 < is_b_type $end
$var wire 32 = instr [31:0] $end
$var wire 32 > imm [31:0] $end
$var wire 7 ? funct7 [6:0] $end
$var wire 3 @ funct3 [2:0] $end
$var wire 32 A dmem_rdata [31:0] $end
$var wire 32 B alu_src_b [31:0] $end
$var wire 32 C alu_result [31:0] $end
$var wire 2 D alu_op [1:0] $end
$var wire 4 E alu_ctrl [3:0] $end
$scope module u_alu $end
$var wire 32 F b [31:0] $end
$var wire 1 + zero $end
$var wire 4 G alu_ctrl [3:0] $end
$var wire 32 H a [31:0] $end
$var parameter 4 I ALU_ADD $end
$var parameter 4 J ALU_AND $end
$var parameter 4 K ALU_OR $end
$var parameter 4 L ALU_SLL $end
$var parameter 4 M ALU_SLT $end
$var parameter 4 N ALU_SLTU $end
$var parameter 4 O ALU_SRA $end
$var parameter 4 P ALU_SRL $end
$var parameter 4 Q ALU_SUB $end
$var parameter 4 R ALU_XOR $end
$var reg 32 S result [31:0] $end
$upscope $end
$scope module u_alu_control $end
$var wire 2 T alu_op [1:0] $end
$var wire 7 U funct7 [6:0] $end
$var wire 3 V funct3 [2:0] $end
$var parameter 4 W ALU_ADD $end
$var parameter 4 X ALU_AND $end
$var parameter 4 Y ALU_OR $end
$var parameter 4 Z ALU_SLL $end
$var parameter 4 [ ALU_SLT $end
$var parameter 4 \ ALU_SLTU $end
$var parameter 4 ] ALU_SRA $end
$var parameter 4 ^ ALU_SRL $end
$var parameter 4 _ ALU_SUB $end
$var parameter 4 ` ALU_XOR $end
$var reg 4 a alu_ctrl [3:0] $end
$upscope $end
$scope module u_decoder $end
$var wire 1 ; is_i_type $end
$var wire 1 5 is_u_type $end
$var wire 5 b rs2 [4:0] $end
$var wire 5 c rs1 [4:0] $end
$var wire 5 d rd [4:0] $end
$var wire 7 e opcode [6:0] $end
$var wire 1 6 is_store $end
$var wire 1 7 is_s_type $end
$var wire 1 8 is_r_type $end
$var wire 1 9 is_load $end
$var wire 1 : is_j_type $end
$var wire 1 < is_b_type $end
$var wire 32 f instr [31:0] $end
$var wire 7 g funct7 [6:0] $end
$var wire 3 h funct3 [2:0] $end
$upscope $end
$scope module u_dmem $end
$var wire 32 i addr [31:0] $end
$var wire 1 # clk $end
$var wire 32 j rdata [31:0] $end
$var wire 1 ( we $end
$var wire 32 k wdata [31:0] $end
$upscope $end
$scope module u_imm_gen $end
$var wire 7 l opcode [6:0] $end
$var wire 32 m instr [31:0] $end
$var reg 32 n imm [31:0] $end
$upscope $end
$scope module u_pc $end
$var wire 1 # clk $end
$var wire 32 o din [31:0] $end
$var wire 1 $ rst_n $end
$var reg 32 p dout [31:0] $end
$upscope $end
$scope module u_regfile $end
$var wire 1 # clk $end
$var wire 5 q rd_addr [4:0] $end
$var wire 5 r rs1_addr [4:0] $end
$var wire 5 s rs2_addr [4:0] $end
$var wire 32 t wdata [31:0] $end
$var wire 1 * we $end
$var wire 32 u rs2_data [31:0] $end
$var wire 32 v rs1_data [31:0] $end
$var integer 32 w i [31:0] $end
$upscope $end
$upscope $end
$scope module u_imem $end
$var wire 32 x addr [31:0] $end
$var wire 32 y data [31:0] $end
$upscope $end
$upscope $end
$enddefinitions $end
$comment Show the parameter values. $end
$dumpall
b100 `
b1000 _
b101 ^
b1101 ]
b11 \
b10 [
b1 Z
b110 Y
b111 X
b0 W
b100 R
b1000 Q
b101 P
b1101 O
b11 N
b10 M
b1 L
b110 K
b111 J
b0 I
$end
#0
$dumpvars
b10011 y
b0 x
b100000 w
b0 v
b0 u
b0 t
b0 s
b0 r
b0 q
b0 p
b100 o
b0 n
b10011 m
b10011 l
b0 k
bx j
b0 i
b0 h
b0 g
b10011 f
b10011 e
b0 d
b0 c
b0 b
b0 a
b0 V
b0 U
b11 T
b0 S
b0 H
b0 G
b0 F
b0 E
b11 D
b0 C
b0 B
bx A
b0 @
b0 ?
b0 >
b10011 =
0<
1;
0:
09
08
07
06
05
b10011 4
b0 3
b100 2
b0 1
b0 0
b0 /
b0 .
b0 -
b0 ,
1+
1*
b0 )
0(
0'
0&
0%
0$
0#
b10011 "
b0 !
$end
#5000
1#
#10000
0#
#15000
1#
#20000
0#
1$
#25000
b1 ,
b1 t
0+
b1 C
b1 S
b1 i
b1 B
b1 F
b1000 2
b1000 o
b1 .
b1 b
b1 s
b1 1
b1 d
b1 q
b1 >
b1 n
b100000000000010010011 "
b100000000000010010011 =
b100000000000010010011 f
b100000000000010010011 m
b100000000000010010011 y
b100 !
b100 )
b100 x
b100 3
b100 p
1#
#30000
0#
#35000
b10 D
b10 T
b1 ,
b1 t
0;
b1 C
b1 S
b1 i
b1 /
b1 H
b1 v
b0 B
b0 F
b1100 2
b1100 o
b110011 l
b10 .
b10 b
b10 s
b1 0
b1 c
b1 r
b10 1
b10 d
b10 q
18
b110011 4
b110011 e
b0 >
b0 n
b0 -
b0 k
b0 u
b1000001000000100110011 "
b1000001000000100110011 =
b1000001000000100110011 f
b1000001000000100110011 m
b1000001000000100110011 y
b1000 !
b1000 )
b1000 x
b1000 3
b1000 p
1#
#40000
0#
#45000
b0 ,
b0 t
1+
b0 C
b0 S
b0 i
b1000 E
b1000 G
b1000 a
b1 B
b1 F
b10000 2
b10000 o
b100000 ?
b100000 U
b100000 g
b11 1
b11 d
b11 q
b1 -
b1 k
b1 u
b1000000001000001000000110110011 "
b1000000001000001000000110110011 =
b1000000001000001000000110110011 f
b1000000001000001000000110110011 m
b1000000001000001000000110110011 y
b1100 !
b1100 )
b1100 x
b1100 3
b1100 p
1#
#50000
0#
#55000
b1 ,
b1 t
0+
b1 C
b1 S
b1 i
b110 E
b110 G
b110 a
b10100 2
b10100 o
b0 ?
b0 U
b0 g
b110 @
b110 V
b110 h
b100 1
b100 d
b100 q
b1000001110001000110011 "
b1000001110001000110011 =
b1000001110001000110011 f
b1000001110001000110011 m
b1000001110001000110011 y
b10000 !
b10000 )
b10000 x
b10000 3
b10000 p
1#
#60000
0#
#65000
b111 E
b111 G
b111 a
b11000 2
b11000 o
b111 @
b111 V
b111 h
b101 1
b101 d
b101 q
b1000001111001010110011 "
b1000001111001010110011 =
b1000001111001010110011 f
b1000001111001010110011 m
b1000001111001010110011 y
b10100 !
b10100 )
b10100 x
b10100 3
b10100 p
1#
#70000
0#
#75000
b100 ,
b100 t
b100 C
b100 S
b100 i
b100 B
b100 F
0*
b100 >
b100 n
b0 /
b0 H
b0 v
b0 E
b0 G
b0 a
b0 D
b0 T
b11100 2
b11100 o
b100011 l
b100 .
b100 b
b100 s
b0 0
b0 c
b0 r
b10 @
b10 V
b10 h
b100 1
b100 d
b100 q
08
17
1(
16
b100011 4
b100011 e
b10000000010001000100011 "
b10000000010001000100011 =
b10000000010001000100011 f
b10000000010001000100011 m
b10000000010001000100011 y
b11000 !
b11000 )
b11000 x
b11000 3
b11000 p
1#
#80000
0#
#85000
1*
1;
b100 C
b100 S
b100 i
b1 ,
b1 t
b100 B
b100 F
b100000 2
b100000 o
b11 l
b110 1
b110 d
b110 q
07
1'
19
0(
06
b11 4
b11 e
b100 >
b100 n
b10000000010001100000011 "
b10000000010001100000011 =
b10000000010001100000011 f
b10000000010001100000011 m
b10000000010001100000011 y
b1 A
b1 j
b11100 !
b11100 )
b11100 x
b11100 3
b11100 p
1#
#90000
0#
#95000
bx A
bx j
0;
b0 D
b0 T
b1000 C
b1000 S
b1000 i
b0 -
b0 k
b0 u
b100100 ,
b100100 t
b1000 B
b1000 F
b101000 2
b101000 o
b1101111 l
b1000 .
b1000 b
b1000 s
b0 @
b0 V
b0 h
b0 1
b0 d
b0 q
1&
1:
0'
09
b1101111 4
b1101111 e
b1000 >
b1000 n
b100000000000000001101111 "
b100000000000000001101111 =
b100000000000000001101111 f
b100000000000000001101111 m
b100000000000000001101111 y
b100000 !
b100000 )
b100000 x
b100000 3
b100000 p
1#
#100000
0#
#105000
b11 D
b11 T
1;
1+
b0 C
b0 S
b0 i
1*
b0 B
b0 F
b0 ,
b0 t
b10011 l
b0 .
b0 b
b0 s
0&
0:
b10011 4
b10011 e
b0 >
b0 n
b101100 2
b101100 o
b10011 "
b10011 =
b10011 f
b10011 m
b10011 y
b101000 !
b101000 )
b101000 x
b101000 3
b101000 p
1#
#110000
0#
#115000
b110000 2
b110000 o
b101100 !
b101100 )
b101100 x
b101100 3
b101100 p
1#
