rtl/imem.v
module imem (
    input wire [31:0] addr, // Address from PC
    output wire [31:0] data // Instruction
);

    // Define memory: 4096 words (16KB)
    reg [31:0] memory [0:4095];

    // Read logic (Combinational / Asynchronous read)
    // RISC-V instructions are 4-byte aligned.
    // We use addr[31:2] to index the word array.
    assign data = memory[addr[31:2]];

endmodule

rtl/dmem.v
module dmem (
    input wire clk,
    input wire we,
    input wire [31:0] addr,
    input wire [31:0] wdata,
    output wire [31:0] rdata
);

    // 16KB Memory
    reg [31:0] memory [0:4095];

    // Write (Synchronous)
    always @(posedge clk) begin
        if (we) begin
            // Word aligned access, masked to 16KB
            memory[addr[13:2]] <= wdata;
        end
    end

    // Read (Asynchronous/Combinational)
    assign rdata = memory[addr[13:2]];

endmodule

rtl/alu.v
module alu (
    input wire [31:0] a,
    input wire [31:0] b,
    input wire [3:0] alu_ctrl, // ALU Control Signal
    output reg [31:0] result,
    output wire zero           // Zero flag (for branches)
);

    // ALU Control Codes (defined arbitrarily for now)
    localparam ALU_ADD  = 4'b0000;
    localparam ALU_SUB  = 4'b1000;
    localparam ALU_SLL  = 4'b0001; // Shift Left Logical
    localparam ALU_SLT  = 4'b0010; // Set Less Than (Signed)
    localparam ALU_SLTU = 4'b0011; // Set Less Than Unsigned
    localparam ALU_XOR  = 4'b0100;
    localparam ALU_SRL  = 4'b0101; // Shift Right Logical
    localparam ALU_SRA  = 4'b1101; // Shift Right Arithmetic
    localparam ALU_OR   = 4'b0110;
    localparam ALU_AND  = 4'b0111;
    localparam ALU_LUI  = 4'b1001; // Load Upper Immediate (Pass B)

    always @(*) begin
        case (alu_ctrl)
            ALU_ADD:  result = a + b;
            ALU_SUB:  result = a - b;
            ALU_SLL:  result = a << b[4:0];
            ALU_SLT:  result = ($signed(a) < $signed(b)) ? 32'd1 : 32'd0;
            ALU_SLTU: result = (a < b) ? 32'd1 : 32'd0;
            ALU_XOR:  result = a ^ b;
            ALU_SRL:  result = a >> b[4:0];
            ALU_SRA:  result = $signed(a) >>> b[4:0];
            ALU_OR:   result = a | b;
            ALU_AND:  result = a & b;
            ALU_LUI:  result = b;
            default:  result = 32'b0;
        endcase
    end

    assign zero = (result == 32'b0);

endmodule

rtl/alu_control.v
module alu_control (
    input wire [1:0] alu_op,    // From Main Control (to be implemented)
    input wire [2:0] funct3,
    input wire [6:0] funct7,
    output reg [3:0] alu_ctrl
);

    // ALU Control Codes (Must match alu.v)
    localparam ALU_ADD  = 4'b0000;
    localparam ALU_SUB  = 4'b1000;
    localparam ALU_SLL  = 4'b0001;
    localparam ALU_SLT  = 4'b0010;
    localparam ALU_SLTU = 4'b0011;
    localparam ALU_XOR  = 4'b0100;
    localparam ALU_SRL  = 4'b0101;
    localparam ALU_SRA  = 4'b1101;
    localparam ALU_OR   = 4'b0110;
    localparam ALU_AND  = 4'b0111;

    always @(*) begin
        case (alu_op)
            2'b00: begin // LW, SW (Add)
                alu_ctrl = ALU_ADD;
            end
            
            2'b01: begin // BEQ, BNE (Sub)
                alu_ctrl = ALU_SUB;
            end

            2'b10: begin // R-type
                case (funct3)
                    3'b000: alu_ctrl = (funct7[5]) ? ALU_SUB : ALU_ADD; // ADD/SUB
                    3'b001: alu_ctrl = ALU_SLL;                         // SLL
                    3'b010: alu_ctrl = ALU_SLT;                         // SLT
                    3'b011: alu_ctrl = ALU_SLTU;                        // SLTU
                    3'b100: alu_ctrl = ALU_XOR;                         // XOR
                    3'b101: alu_ctrl = (funct7[5]) ? ALU_SRA : ALU_SRL; // SRL/SRA
                    3'b110: alu_ctrl = ALU_OR;                          // OR
                    3'b111: alu_ctrl = ALU_AND;                         // AND
                    default: alu_ctrl = ALU_ADD;
                endcase
            end

            2'b11: begin // I-type (Immediate Arithmetic)
                case (funct3)
                    3'b000: alu_ctrl = ALU_ADD;                         // ADDI
                    3'b001: alu_ctrl = ALU_SLL;                         // SLLI
                    3'b010: alu_ctrl = ALU_SLT;                         // SLTI
                    3'b011: alu_ctrl = ALU_SLTU;                        // SLTIU
                    3'b100: alu_ctrl = ALU_XOR;                         // XORI
                    3'b101: alu_ctrl = (funct7[5]) ? ALU_SRA : ALU_SRL; // SRLI/SRAI
                    3'b110: alu_ctrl = ALU_OR;                          // ORI
                    3'b111: alu_ctrl = ALU_AND;                         // ANDI
                    default: alu_ctrl = ALU_ADD;
                endcase
            end

            default: alu_ctrl = ALU_ADD;
        endcase
    end

endmodule

rtl/imm_gen.v
module imm_gen (
    input wire [31:0] instr,
    output reg [31:0] imm
);

    wire [6:0] opcode = instr[6:0];

    always @(*) begin
        case (opcode)
            // I-type: [31:20] -> imm[11:0]
            // ADDI, LW, JALR, etc.
            7'b0010011, 7'b0000011, 7'b1100111: 
                imm = {{20{instr[31]}}, instr[31:20]};

            // S-type: [31:25] + [11:7] -> imm[11:0]
            // SW
            7'b0100011: 
                imm = {{20{instr[31]}}, instr[31:25], instr[11:7]};

            // B-type: [31], [7], [30:25], [11:8] -> imm[12:1]
            // BEQ, BNE, etc.
            7'b1100011: 
                imm = {{20{instr[31]}}, instr[7], instr[30:25], instr[11:8], 1'b0};

            // U-type: [31:12] -> imm[31:12]
            // LUI, AUIPC
            7'b0110111, 7'b0010111: 
                imm = {instr[31:12], 12'b0};

            // J-type: [31], [19:12], [20], [30:21] -> imm[20:1]
            // JAL
            7'b1101111: 
                imm = {{12{instr[31]}}, instr[19:12], instr[20], instr[30:21], 1'b0};

            default: 
                imm = 32'b0;
        endcase
    end

endmodule

rtl/regfile.v
module regfile (
    input wire clk,
    input wire we,            // Write Enable
    input wire [4:0] rs1_addr, // Read Address 1
    input wire [4:0] rs2_addr, // Read Address 2
    input wire [4:0] rd_addr,  // Write Address
    input wire [31:0] wdata,   // Write Data
    output wire [31:0] rs1_data, // Read Data 1
    output wire [31:0] rs2_data  // Read Data 2
);

    // 32 registers of 32-bit width
    reg [31:0] regs [0:31];

    integer i;

    // Initialize registers to 0
    initial begin
        for (i = 0; i < 32; i = i + 1) begin
            regs[i] = 32'h0;
        end
        regs[2] = 32'h4000; // Initialize SP to 16KB
    end

    // Write operation (Synchronous)
    // Note: x0 is hardwired to 0, so we never write to it.
    always @(posedge clk) begin
        if (we && (rd_addr != 5'b00000)) begin
            regs[rd_addr] <= wdata;
        end
    end

    // Read operation (Asynchronous)
    // If reading x0, always return 0.
    assign rs1_data = (rs1_addr == 5'b0) ? 32'b0 : regs[rs1_addr];
    assign rs2_data = (rs2_addr == 5'b0) ? 32'b0 : regs[rs2_addr];

endmodule

rtl/control_unit.v
module control_unit (
    input wire [6:0] opcode,
    output reg branch,
    output reg jump,
    output reg mem_read,
    output reg mem_to_reg,
    output reg [1:0] alu_op,
    output reg mem_write,
    output reg alu_src,
    output reg reg_write
);

    always @(*) begin
        // Default values (prevent latches)
        branch     = 0;
        jump       = 0;
        mem_read   = 0;
        mem_to_reg = 0;
        alu_op     = 2'b00;
        mem_write  = 0;
        alu_src    = 0;
        reg_write  = 0;

        case (opcode)
            // R-type: ADD, SUB, AND, OR, etc.
            7'b0110011: begin
                reg_write = 1;
                alu_op    = 2'b10;
            end

            // I-type: ADDI, ANDI, etc.
            7'b0010011: begin
                alu_src   = 1; // Use Immediate
                reg_write = 1;
                alu_op    = 2'b11; // I-type ALU encoding
            end

            // Load: LW
            7'b0000011: begin
                alu_src    = 1;
                mem_to_reg = 1;
                reg_write  = 1;
                mem_read   = 1;
                alu_op     = 2'b00; // Add (Base + Offset)
            end

            // Store: SW
            7'b0100011: begin
                alu_src   = 1;
                mem_write = 1;
                alu_op    = 2'b00; // Add (Base + Offset)
            end

            // Branch: BEQ
            7'b1100011: begin
                branch = 1;
                alu_op = 2'b01; // Sub (Comparison)
            end

            // Jump: JAL
            7'b1101111: begin
                jump      = 1;
                reg_write = 1;
                // ALU op doesn't matter for JAL, but let's keep it clean
            end

            // U-type: LUI, AUIPC (Simplified handling)
            7'b0110111, 7'b0010111: begin
                alu_src   = 1;
                reg_write = 1;
                // TODO: Proper ALU op for U-type
            end

            default: begin
                // NOP or invalid
            end
        endcase
    end

endmodule

rtl/decoder.v
module decoder (
    input wire [31:0] instr,
    output wire [6:0] opcode,
    output wire [2:0] funct3,
    output wire [6:0] funct7,
    output wire [4:0] rd,
    output wire [4:0] rs1,
    output wire [4:0] rs2,
    // Control signals (placeholder for now)
    output wire is_r_type,
    output wire is_i_type,
    output wire is_s_type,
    output wire is_b_type,
    output wire is_u_type,
    output wire is_j_type,
    output wire is_load,  // New: Explicit Load signal
    output wire is_store  // New: Explicit Store signal
);

    // Field extraction
    assign opcode = instr[6:0];
    assign rd     = instr[11:7];
    assign funct3 = instr[14:12];
    assign rs1    = instr[19:15];
    assign rs2    = instr[24:20];
    assign funct7 = instr[31:25];

    // Instruction Type Decoding
    
    // R-type: 0110011 (OP)
    assign is_r_type = (opcode == 7'b0110011);

    // I-type: 0010011 (OP-IMM), 0000011 (LOAD), 1100111 (JALR)
    assign is_i_type = (opcode == 7'b0010011) || (opcode == 7'b0000011) || (opcode == 7'b1100111);

    // S-type: 0100011 (STORE)
    assign is_s_type = (opcode == 7'b0100011);

    // B-type: 1100011 (BRANCH)
    assign is_b_type = (opcode == 7'b1100011);

    // U-type: 0110111 (LUI), 0010111 (AUIPC)
    assign is_u_type = (opcode == 7'b0110111) || (opcode == 7'b0010111);

    // J-type: 1101111 (JAL)
    assign is_j_type = (opcode == 7'b1101111);

    // Specific Opcode Checks
    assign is_load  = (opcode == 7'b0000011);
    assign is_store = (opcode == 7'b0100011);

endmodule

rtl/pc.v
module pc (
    input wire clk,
    input wire rst_n,      // Active low reset
    input wire [31:0] din, // Next PC value
    output reg [31:0] dout // Current PC value
);

    always @(posedge clk or negedge rst_n) begin
        if (!rst_n) begin
            dout <= 32'h00000000; // Reset address
        end else begin
            dout <= din;
        end
    end

endmodule

rtl/core.v
module core (
    input wire clk,
    input wire rst_n,
    input wire [31:0] instr,   // Instruction from IMEM
    output wire [31:0] pc_addr // PC output to IMEM
);

    wire [31:0] pc_next;
    wire [31:0] pc_curr;

    // Instantiate PC
    pc u_pc (
        .clk(clk),
        .rst_n(rst_n),
        .din(pc_next),
        .dout(pc_curr)
    );

    // Decoder signals
    wire [6:0] opcode;
    wire [2:0] funct3;
    wire [6:0] funct7;
    wire [4:0] rd;
    wire [4:0] rs1;
    wire [4:0] rs2;
    wire is_r_type, is_i_type, is_s_type, is_b_type, is_u_type, is_j_type;
    wire is_load, is_store;

    // RegFile signals
    wire reg_write;
    wire [31:0] wdata; // Data to write back to RegFile
    wire [31:0] rs1_data;
    wire [31:0] rs2_data;

    // ALU signals
    wire [31:0] alu_result;
    wire zero_flag;
    wire [3:0] alu_ctrl;
    wire [31:0] alu_src_b; // MUX output for ALU operand B

    // Control signals
    wire branch;
    wire jump;
    wire mem_read; // Not used yet (for future)
    wire mem_to_reg;
    wire [1:0] alu_op;
    wire mem_write;
    wire alu_src;
    // wire reg_write; // Removed duplicate declaration

    wire [31:0] imm;
    wire [31:0] dmem_rdata;

    // Instantiate Decoder
    decoder u_decoder (
        .instr(instr),
        .opcode(opcode),
        .funct3(funct3),
        .funct7(funct7),
        .rd(rd),
        .rs1(rs1),
        .rs2(rs2),
        .is_r_type(is_r_type),
        .is_i_type(is_i_type),
        .is_s_type(is_s_type),
        .is_b_type(is_b_type),
        .is_u_type(is_u_type),
        .is_j_type(is_j_type),
        .is_load(is_load),
        .is_store(is_store)
    );

    // Instantiate Control Unit
    control_unit u_control_unit (
        .opcode(opcode),
        .branch(branch),
        .jump(jump),
        .mem_read(mem_read),
        .mem_to_reg(mem_to_reg),
        .alu_op(alu_op),
        .mem_write(mem_write),
        .alu_src(alu_src),
        .reg_write(reg_write)
    );

    // Instantiate Register File
    regfile u_regfile (
        .clk(clk),
        .we(reg_write),
        .rs1_addr(rs1),
        .rs2_addr(rs2),
        .rd_addr(rd),
        .wdata(wdata),
        .rs1_data(rs1_data),
        .rs2_data(rs2_data)
    );

    // Instantiate Immediate Generator
    imm_gen u_imm_gen (
        .instr(instr),
        .imm(imm)
    );

    // Instantiate ALU Control
    alu_control u_alu_control (
        .alu_op(alu_op),
        .funct3(funct3),
        .funct7(funct7),
        .alu_ctrl(alu_ctrl)
    );

    // MUX for ALU operand B
    assign alu_src_b = alu_src ? imm : rs2_data;

    // Instantiate ALU
    alu u_alu (
        .a(rs1_data),
        .b(alu_src_b), 
        .alu_ctrl(alu_ctrl),
        .result(alu_result),
        .zero(zero_flag)
    );

    // Instantiate Data Memory
    dmem u_dmem (
        .clk(clk),
        .we(mem_write),
        .addr(alu_result),
        .wdata(rs2_data),
        .rdata(dmem_rdata)
    );

    // Write back data MUX
    // JAL and JALR both write PC+4 to rd
    assign wdata = mem_to_reg ? dmem_rdata : 
                   jump       ? (pc_curr + 32'd4) : 
                   alu_result;

    // Branch/Jump Logic
    reg branch_condition_met;
    
    always @(*) begin
        case (funct3)
            3'b000: branch_condition_met = zero_flag;          // BEQ
            3'b001: branch_condition_met = !zero_flag;         // BNE
            3'b100: branch_condition_met = (alu_result != 0);  // BLT (ALU does SLT, so result is 1 if a < b)
            3'b101: branch_condition_met = (alu_result == 0);  // BGE (ALU does SLT, so result is 0 if a >= b)
            3'b110: branch_condition_met = (alu_result != 0);  // BLTU (ALU does SLTU)
            3'b111: branch_condition_met = (alu_result == 0);  // BGEU (ALU does SLTU)
            default: branch_condition_met = 0;
        endcase
    end

    wire branch_taken = branch && branch_condition_met;
    
    // JALR Logic
    // JALR target = (rs1 + imm) & ~1
    // Note: In our single cycle implementation, rs1 is available at rs1_data
    // and imm is available at imm.
    // We can reuse the ALU to calculate rs1 + imm if we set alu_src_b = imm and alu_ctrl = ADD.
    // But JALR is an I-type instruction (opcode 1100111).
    // Let's check if we can just use a dedicated adder or reuse ALU.
    // For simplicity, let's use a dedicated calculation here to avoid complex ALU control changes for now.
    wire [31:0] jalr_target = (rs1_data + imm) & 32'hFFFFFFFE;

    // PC Next MUX
    // Priority: JALR > JAL > Branch > Next
    // Note: We need a signal to distinguish JAL and JALR.
    // Currently 'jump' is high for JAL. We need to update Control Unit or Decoder.
    // Let's use opcode check for JALR here for simplicity, or update decoder.
    wire is_jalr = (opcode == 7'b1100111);

    assign pc_next = is_jalr      ? jalr_target :
                     jump         ? (pc_curr + imm) : 
                     branch_taken ? (pc_curr + imm) : 
                     (pc_curr + 32'd4);

    // Output current PC to IMEM
    assign pc_addr = pc_curr;

endmodule

tb/core_tb.v
`timescale 1ns / 1ps

module core_tb;

    reg clk;
    reg rst_n;
    wire [31:0] instr;
    wire [31:0] pc_addr;

    // Instantiate Core
    core u_core (
        .clk(clk),
        .rst_n(rst_n),
        .instr(instr),
        .pc_addr(pc_addr)
    );

    // Instantiate IMEM
    imem u_imem (
        .addr(pc_addr),
        .data(instr)
    );

    // Clock generation
    initial begin
        clk = 0;
        forever #5 clk = ~clk;
    end

    // Test logic
    initial begin
        $dumpfile("wave.vcd");
        $dumpvars(0, core_tb);

        // Reset
        rst_n = 0;
        #20;
        rst_n = 1;

        // Run simulation for a few cycles
        #500;
        $finish;
    end

    // Monitor
    initial begin
        $monitor("Time=%0t | PC=%h | Instr=%h | Op=%b | rd=%d | rs1_d=%h | imm=%h | alu_res=%h | we=%b | wd=%h", 
                 $time, pc_addr, instr, u_core.opcode, u_core.rd, u_core.rs1_data, u_core.imm, u_core.alu_result, u_core.reg_write, u_core.wdata);
    end

endmodule

sim/wave.vcd
$date
	Tue Dec  2 11:53:43 2025
$end
$version
	Icarus Verilog
$end
$timescale
	1ps
$end
$scope module core_tb $end
$var wire 32 ! pc_addr [31:0] $end
$var wire 32 " instr [31:0] $end
$var reg 1 # clk $end
$var reg 1 $ rst_n $end
$scope module u_core $end
$var wire 1 % branch_taken $end
$var wire 1 # clk $end
$var wire 32 & jalr_target [31:0] $end
$var wire 32 ' pc_addr [31:0] $end
$var wire 1 $ rst_n $end
$var wire 1 ( zero_flag $end
$var wire 32 ) wdata [31:0] $end
$var wire 32 * rs2_data [31:0] $end
$var wire 5 + rs2 [4:0] $end
$var wire 32 , rs1_data [31:0] $end
$var wire 5 - rs1 [4:0] $end
$var wire 1 . reg_write $end
$var wire 5 / rd [4:0] $end
$var wire 32 0 pc_next [31:0] $end
$var wire 32 1 pc_curr [31:0] $end
$var wire 7 2 opcode [6:0] $end
$var wire 1 3 mem_write $end
$var wire 1 4 mem_to_reg $end
$var wire 1 5 mem_read $end
$var wire 1 6 jump $end
$var wire 1 7 is_u_type $end
$var wire 1 8 is_store $end
$var wire 1 9 is_s_type $end
$var wire 1 : is_r_type $end
$var wire 1 ; is_load $end
$var wire 1 < is_jalr $end
$var wire 1 = is_j_type $end
$var wire 1 > is_i_type $end
$var wire 1 ? is_b_type $end
$var wire 32 @ instr [31:0] $end
$var wire 32 A imm [31:0] $end
$var wire 7 B funct7 [6:0] $end
$var wire 3 C funct3 [2:0] $end
$var wire 32 D dmem_rdata [31:0] $end
$var wire 1 E branch $end
$var wire 32 F alu_src_b [31:0] $end
$var wire 1 G alu_src $end
$var wire 32 H alu_result [31:0] $end
$var wire 2 I alu_op [1:0] $end
$var wire 4 J alu_ctrl [3:0] $end
$var reg 1 K branch_condition_met $end
$scope module u_alu $end
$var wire 32 L b [31:0] $end
$var wire 1 ( zero $end
$var wire 4 M alu_ctrl [3:0] $end
$var wire 32 N a [31:0] $end
$var parameter 4 O ALU_ADD $end
$var parameter 4 P ALU_AND $end
$var parameter 4 Q ALU_OR $end
$var parameter 4 R ALU_SLL $end
$var parameter 4 S ALU_SLT $end
$var parameter 4 T ALU_SLTU $end
$var parameter 4 U ALU_SRA $end
$var parameter 4 V ALU_SRL $end
$var parameter 4 W ALU_SUB $end
$var parameter 4 X ALU_XOR $end
$var reg 32 Y result [31:0] $end
$upscope $end
$scope module u_alu_control $end
$var wire 7 Z funct7 [6:0] $end
$var wire 3 [ funct3 [2:0] $end
$var wire 2 \ alu_op [1:0] $end
$var parameter 4 ] ALU_ADD $end
$var parameter 4 ^ ALU_AND $end
$var parameter 4 _ ALU_OR $end
$var parameter 4 ` ALU_SLL $end
$var parameter 4 a ALU_SLT $end
$var parameter 4 b ALU_SLTU $end
$var parameter 4 c ALU_SRA $end
$var parameter 4 d ALU_SRL $end
$var parameter 4 e ALU_SUB $end
$var parameter 4 f ALU_XOR $end
$var reg 4 g alu_ctrl [3:0] $end
$upscope $end
$scope module u_control_unit $end
$var wire 7 h opcode [6:0] $end
$var reg 2 i alu_op [1:0] $end
$var reg 1 G alu_src $end
$var reg 1 E branch $end
$var reg 1 6 jump $end
$var reg 1 5 mem_read $end
$var reg 1 4 mem_to_reg $end
$var reg 1 3 mem_write $end
$var reg 1 . reg_write $end
$upscope $end
$scope module u_decoder $end
$var wire 1 > is_i_type $end
$var wire 1 7 is_u_type $end
$var wire 5 j rs2 [4:0] $end
$var wire 5 k rs1 [4:0] $end
$var wire 5 l rd [4:0] $end
$var wire 7 m opcode [6:0] $end
$var wire 1 8 is_store $end
$var wire 1 9 is_s_type $end
$var wire 1 : is_r_type $end
$var wire 1 ; is_load $end
$var wire 1 = is_j_type $end
$var wire 1 ? is_b_type $end
$var wire 32 n instr [31:0] $end
$var wire 7 o funct7 [6:0] $end
$var wire 3 p funct3 [2:0] $end
$upscope $end
$scope module u_dmem $end
$var wire 32 q addr [31:0] $end
$var wire 1 # clk $end
$var wire 32 r rdata [31:0] $end
$var wire 1 3 we $end
$var wire 32 s wdata [31:0] $end
$upscope $end
$scope module u_imm_gen $end
$var wire 7 t opcode [6:0] $end
$var wire 32 u instr [31:0] $end
$var reg 32 v imm [31:0] $end
$upscope $end
$scope module u_pc $end
$var wire 1 # clk $end
$var wire 32 w din [31:0] $end
$var wire 1 $ rst_n $end
$var reg 32 x dout [31:0] $end
$upscope $end
$scope module u_regfile $end
$var wire 1 # clk $end
$var wire 5 y rd_addr [4:0] $end
$var wire 5 z rs1_addr [4:0] $end
$var wire 5 { rs2_addr [4:0] $end
$var wire 32 | wdata [31:0] $end
$var wire 1 . we $end
$var wire 32 } rs2_data [31:0] $end
$var wire 32 ~ rs1_data [31:0] $end
$var integer 32 !" i [31:0] $end
$upscope $end
$upscope $end
$scope module u_imem $end
$var wire 32 "" addr [31:0] $end
$var wire 32 #" data [31:0] $end
$upscope $end
$upscope $end
$enddefinitions $end
$comment Show the parameter values. $end
$dumpall
b100 f
b1000 e
b101 d
b1101 c
b11 b
b10 a
b1 `
b110 _
b111 ^
b0 ]
b100 X
b1000 W
b101 V
b1101 U
b11 T
b10 S
b1 R
b110 Q
b111 P
b0 O
$end
#0
$dumpvars
b10011 #"
b0 ""
b100000 !"
b0 ~
b0 }
b0 |
b0 {
b0 z
b0 y
b0 x
b100 w
b0 v
b10011 u
b10011 t
b0 s
bx r
b0 q
b0 p
b0 o
b10011 n
b10011 m
b0 l
b0 k
b0 j
b11 i
b10011 h
b0 g
b11 \
b0 [
b0 Z
b0 Y
b0 N
b0 M
b0 L
1K
b0 J
b11 I
b0 H
1G
b0 F
0E
bx D
b0 C
b0 B
b0 A
b10011 @
0?
1>
0=
0<
0;
0:
09
08
07
06
05
04
03
b10011 2
b0 1
b100 0
b0 /
1.
b0 -
b0 ,
b0 +
b0 *
b0 )
1(
b0 '
b0 &
0%
0$
0#
b10011 "
b0 !
$end
#5000
1#
#10000
0#
#15000
1#
#20000
0#
1$
#25000
b1 )
b1 |
0K
0(
b1 H
b1 Y
b1 q
b1000 0
b1000 w
b1 F
b1 L
b1 +
b1 j
b1 {
b1 /
b1 l
b1 y
b1 A
b1 v
b100000000000010010011 "
b100000000000010010011 @
b100000000000010010011 n
b100000000000010010011 u
b100000000000010010011 #"
b100 !
b100 '
b100 ""
b100 1
b100 x
1#
#30000
0#
#35000
b1 )
b1 |
0>
b1 H
b1 Y
b1 q
b1100 0
b1100 w
b1 ,
b1 N
b1 ~
1.
0G
b10 I
b10 \
b10 i
b0 &
b0 F
b0 L
b110011 t
b10 +
b10 j
b10 {
b1 -
b1 k
b1 z
b10 /
b10 l
b10 y
1:
b110011 2
b110011 h
b110011 m
b0 A
b0 v
b0 *
b0 s
b0 }
b1000001000000100110011 "
b1000001000000100110011 @
b1000001000000100110011 n
b1000001000000100110011 u
b1000001000000100110011 #"
b1000 !
b1000 '
b1000 ""
b1000 1
b1000 x
1#
#40000
0#
#45000
b0 )
b0 |
1K
1(
b0 H
b0 Y
b0 q
b10000 0
b10000 w
b1000 J
b1000 M
b1000 g
b1 F
b1 L
b100000 B
b100000 Z
b100000 o
b11 /
b11 l
b11 y
b1 *
b1 s
b1 }
b1000000001000001000000110110011 "
b1000000001000001000000110110011 @
b1000000001000001000000110110011 n
b1000000001000001000000110110011 u
b1000000001000001000000110110011 #"
b1100 !
b1100 '
b1100 ""
b1100 1
b1100 x
1#
#50000
0#
#55000
b1 )
b1 |
0(
b1 H
b1 Y
b1 q
b10100 0
b10100 w
1K
b110 J
b110 M
b110 g
b0 B
b0 Z
b0 o
b110 C
b110 [
b110 p
b100 /
b100 l
b100 y
b1000001110001000110011 "
b1000001110001000110011 @
b1000001110001000110011 n
b1000001110001000110011 u
b1000001110001000110011 #"
b10000 !
b10000 '
b10000 ""
b10000 1
b10000 x
1#
#60000
0#
#65000
b11000 0
b11000 w
0K
b111 J
b111 M
b111 g
b111 C
b111 [
b111 p
b101 /
b101 l
b101 y
b1000001111001010110011 "
b1000001111001010110011 @
b1000001111001010110011 n
b1000001111001010110011 u
b1000001111001010110011 #"
b10100 !
b10100 '
b10100 ""
b10100 1
b10100 x
1#
#70000
0#
#75000
b100 )
b100 |
b100 &
b100 H
b100 Y
b100 q
b100 F
b100 L
b11100 0
b11100 w
b100 A
b100 v
b0 ,
b0 N
b0 ~
b0 J
b0 M
b0 g
13
1G
0.
b0 I
b0 \
b0 i
b100011 t
b100 +
b100 j
b100 {
b0 -
b0 k
b0 z
b10 C
b10 [
b10 p
b100 /
b100 l
b100 y
0:
19
18
b100011 2
b100011 h
b100011 m
b10000000010001000100011 "
b10000000010001000100011 @
b10000000010001000100011 n
b10000000010001000100011 u
b10000000010001000100011 #"
b11000 !
b11000 '
b11000 ""
b11000 1
b11000 x
1#
#80000
0#
#85000
1>
b1 )
b1 |
b100 H
b100 Y
b100 q
b100000 0
b100000 w
15
1.
14
1G
03
b100 &
b100 F
b100 L
b11 t
b110 /
b110 l
b110 y
09
1;
08
b11 2
b11 h
b11 m
b100 A
b100 v
b10000000010001100000011 "
b10000000010001100000011 @
b10000000010001100000011 n
b10000000010001100000011 u
b10000000010001100000011 #"
b1 D
b1 r
b11100 !
b11100 '
b11100 ""
b11100 1
b11100 x
1#
#90000
0#
#95000
1K
1(
bx D
bx r
0>
b100100 )
b100100 |
b0 H
b0 Y
b0 q
b101000 0
b101000 w
b0 *
b0 s
b0 }
16
1.
0G
04
05
b1000 &
b0 F
b0 L
b1101111 t
b1000 +
b1000 j
b1000 {
b0 C
b0 [
b0 p
b0 /
b0 l
b0 y
1=
0;
b1101111 2
b1101111 h
b1101111 m
b1000 A
b1000 v
b100000000000000001101111 "
b100000000000000001101111 @
b100000000000000001101111 n
b100000000000000001101111 u
b100000000000000001101111 #"
b100000 !
b100000 '
b100000 ""
b100000 1
b100000 x
1#
#100000
0#
#105000
1>
b11 I
b11 \
b11 i
1G
1.
06
b0 &
b101100 0
b101100 w
b0 )
b0 |
b10011 t
b0 +
b0 j
b0 {
0=
b10011 2
b10011 h
b10011 m
b0 A
b0 v
b10011 "
b10011 @
b10011 n
b10011 u
b10011 #"
b101000 !
b101000 '
b101000 ""
b101000 1
b101000 x
1#
#110000
0#
#115000
b110000 0
b110000 w
b101100 !
b101100 '
b101100 ""
b101100 1
b101100 x
1#
#120000
0#
#125000
b1 )
b1 |
0K
0(
b1 H
b1 Y
b1 q
b110100 0
b110100 w
b1 *
b1 s
b1 }
b1 F
b1 L
b1 +
b1 j
b1 {
b101 /
b101 l
b101 y
b1 A
b1 v
b100000000001010010011 "
b100000000001010010011 @
b100000000001010010011 n
b100000000001010010011 u
b100000000001010010011 #"
b110000 !
b110000 '
b110000 ""
b110000 1
b110000 x
1#
#130000
0#
#135000
b0 )
b0 |
1(
0>
0%
b0 H
b0 Y
b0 q
b111000 0
b111000 w
b1 ,
b1 N
b1 ~
0K
b1000 J
b1000 M
b1000 g
1E
0.
0G
b1 I
b1 \
b1 i
b1000 &
b1 F
b1 L
b1100011 t
b101 +
b101 j
b101 {
b101 -
b101 k
b101 z
b1 C
b1 [
b1 p
b1000 /
b1000 l
b1000 y
1?
b1100011 2
b1100011 h
b1100011 m
b1000 A
b1000 v
b10100101001010001100011 "
b10100101001010001100011 @
b10100101001010001100011 n
b10100101001010001100011 u
b10100101001010001100011 #"
b110100 !
b110100 '
b110100 ""
b110100 1
b110100 x
1#
#140000
0#
#145000
1>
b0 F
b0 L
b111100 0
b111100 w
b0 *
b0 s
b0 }
b0 ,
b0 N
b0 ~
1K
b0 J
b0 M
b0 g
1.
1G
b11 I
b11 \
b11 i
0E
b0 &
b10011 t
b0 +
b0 j
b0 {
b0 -
b0 k
b0 z
b0 C
b0 [
b0 p
b0 /
b0 l
b0 y
0?
b10011 2
b10011 h
b10011 m
b0 A
b0 v
b10011 "
b10011 @
b10011 n
b10011 u
b10011 #"
b111000 !
b111000 '
b111000 ""
b111000 1
b111000 x
1#
#150000
0#
#155000
0K
b1000000 )
b1000000 |
0(
b1 H
b1 Y
b1 q
b1 ,
b1 N
b1 ~
b0 0
b0 w
16
1.
1G
b0 I
b0 \
b0 i
b1100111 t
b1 -
b1 k
b1 z
1<
b1100111 2
b1100111 h
b1100111 m
b1000000001100111 "
b1000000001100111 @
b1000000001100111 n
b1000000001100111 u
b1000000001100111 #"
b111100 !
b111100 '
b111100 ""
b111100 1
b111100 x
1#
#160000
0#
#165000
1K
b100 0
b100 w
1(
b0 H
b0 Y
b0 q
b0 ,
b0 N
b0 ~
1>
b11 I
b11 \
b11 i
1.
1G
06
b0 )
b0 |
b10011 t
b0 -
b0 k
b0 z
0<
b10011 2
b10011 h
b10011 m
b10011 "
b10011 @
b10011 n
b10011 u
b10011 #"
b0 !
b0 '
b0 ""
b0 1
b0 x
1#
#170000
0#
#175000
b1 )
b1 |
0K
0(
b1 H
b1 Y
b1 q
b1000 0
b1000 w
b1 *
b1 s
b1 }
b1 F
b1 L
b1 +
b1 j
b1 {
b1 /
b1 l
b1 y
b1 A
b1 v
b100000000000010010011 "
b100000000000010010011 @
b100000000000010010011 n
b100000000000010010011 u
b100000000000010010011 #"
b100 !
b100 '
b100 ""
b100 1
b100 x
1#
#180000
0#
#185000
b10 )
b10 |
0>
b10 H
b10 Y
b10 q
b1100 0
b1100 w
b1 ,
b1 N
b1 ~
1.
0G
b10 I
b10 \
b10 i
b0 &
b1 F
b1 L
b110011 t
b10 +
b10 j
b10 {
b1 -
b1 k
b1 z
b10 /
b10 l
b10 y
1:
b110011 2
b110011 h
b110011 m
b0 A
b0 v
b1000001000000100110011 "
b1000001000000100110011 @
b1000001000000100110011 n
b1000001000000100110011 u
b1000001000000100110011 #"
b1000 !
b1000 '
b1000 ""
b1000 1
b1000 x
1#
#190000
0#
#195000
b11111111111111111111111111111111 )
b11111111111111111111111111111111 |
b11111111111111111111111111111111 H
b11111111111111111111111111111111 Y
b11111111111111111111111111111111 q
b10000 0
b10000 w
b1000 J
b1000 M
b1000 g
b10 F
b10 L
b100000 B
b100000 Z
b100000 o
b11 /
b11 l
b11 y
b10 *
b10 s
b10 }
b1000000001000001000000110110011 "
b1000000001000001000000110110011 @
b1000000001000001000000110110011 n
b1000000001000001000000110110011 u
b1000000001000001000000110110011 #"
b1100 !
b1100 '
b1100 ""
b1100 1
b1100 x
1#
#200000
0#
